modm/__init__.py
modm/main.py
modm_cli-0.1.0.dist-info/METADATA
modm_cli-0.1.0.dist-info/RECORD
modm_cli-0.1.0.dist-info/WHEEL
modm_cli-0.1.0.dist-info/entry_points.txt
modm_cli-0.1.0.dist-info/top_level.txt
